.gitignore
CHANGES.rst
CONTRIBUTORS.rst
MANIFEST.in
README.rst
setup.py
docs/LICENSE.GPL
docs/LICENSE.rst
src/collective/__init__.py
src/collective.ckeditortemplates.egg-info/PKG-INFO
src/collective.ckeditortemplates.egg-info/SOURCES.txt
src/collective.ckeditortemplates.egg-info/dependency_links.txt
src/collective.ckeditortemplates.egg-info/entry_points.txt
src/collective.ckeditortemplates.egg-info/namespace_packages.txt
src/collective.ckeditortemplates.egg-info/not-zip-safe
src/collective.ckeditortemplates.egg-info/requires.txt
src/collective.ckeditortemplates.egg-info/top_level.txt
src/collective/ckeditortemplates/__init__.py
src/collective/ckeditortemplates/cktemplate.py
src/collective/ckeditortemplates/cktemplate_icon.gif
src/collective/ckeditortemplates/cktemplatefolder_icon.gif
src/collective/ckeditortemplates/configure.zcml
src/collective/ckeditortemplates/profiles.zcml
src/collective/ckeditortemplates/setuphandlers.py
src/collective/ckeditortemplates/testing.py
src/collective/ckeditortemplates/upgrades.py
src/collective/ckeditortemplates/browser/__init__.py
src/collective/ckeditortemplates/browser/cktemplatelisting.py
src/collective/ckeditortemplates/browser/configure.zcml
src/collective/ckeditortemplates/browser/tests/__init__.py
src/collective/ckeditortemplates/browser/tests/test_cktemplatelisting.py
src/collective/ckeditortemplates/locales/en/LC_MESSAGES/collective.ckeditortemplates.po
src/collective/ckeditortemplates/locales/en/LC_MESSAGES/plone.po
src/collective/ckeditortemplates/locales/es/LC_MESSAGES/collective.ckeditortemplates.po
src/collective/ckeditortemplates/locales/es/LC_MESSAGES/plone.po
src/collective/ckeditortemplates/locales/fr/LC_MESSAGES/collective.ckeditortemplates.po
src/collective/ckeditortemplates/locales/fr/LC_MESSAGES/plone.po
src/collective/ckeditortemplates/locales/nl/LC_MESSAGES/collective.ckeditortemplates.po
src/collective/ckeditortemplates/locales/nl/LC_MESSAGES/plone.po
src/collective/ckeditortemplates/profiles/default/collective.ckeditortemplates_various.txt
src/collective/ckeditortemplates/profiles/default/controlpanel.xml
src/collective/ckeditortemplates/profiles/default/metadata.xml
src/collective/ckeditortemplates/profiles/default/types.xml
src/collective/ckeditortemplates/profiles/default/workflows.xml
src/collective/ckeditortemplates/profiles/default/types/cktemplate.xml
src/collective/ckeditortemplates/profiles/default/types/cktemplatefolder.xml
